{
    "format_version": "1.13.0",
    "minecraft:weighted_random_feature": {
        "description": {
            "identifier": "ff:wither_rose/wither_rose_valley_flower_feature"
        },
        "features": [
            [
                "ff:wither_rose/wither_rose_tall_feature",
                15
            ],
            [
                "ff:wither_rose/wither_rose_short_feature",
                17
            ],
            [
                "ff:wither_rose/wither_rose_large_feature",
                12
            ]
        ]
    }
}