{
  "format_version": "1.16",
  "minecraft:recipe_shaped": {
    "description": {
      "identifier": "craft:purple_hard_glass"
    },
    "tags": [
      "crafting_table"
    ],
    "pattern": [
      "FFF",
      "GGG",
      "FFF"
    ],
    "key": {
      "F": {
        "item": "cav:feldspar"
      },
      "G": {
        "item": "minecraft:stained_glass",
        "data": 10
      }
    },
    "result": {
      "item": "minecraft:hard_stained_glass",
      "data": 10,
      "count": 3
    }
  }
}
