{
  "format_version": "1.13.0",
  "minecraft:feature_rules": {
    "description": {
      "identifier": "ff:pink_rose_bush_rule",
      "places_feature": "ff:oak_bush_feature"
    },
    "conditions": {
      "placement_pass": "before_surface_pass",
      "minecraft:biome_filter": [
        {
          "any_of": [
            {
              "test": "has_biome_tag",
              "operator": "==",
              "value": "plains"
            }
          ]
        }
      ]
    },
		"distribution": {
			"iterations": 65,

			"x": {
				"distribution": "uniform",
				"extent": [0, 16]
			},
			"z": {
				"distribution": "uniform",
				"extent": [0, 16]
			},
			"y": "t.in = q.noise(v.worldx / 1024, v.worldz / 1024) + q.noise(v.worldx, v.worldz) * 0.05; return (t.in > -0.4 && t.in < -0.2 ? q.heightmap(v.worldx, v.worldz) : -65);"
		}
  }
}